grpc_gateway_wrapper/__init__.py
grpc_gateway_wrapper/__main__.py
grpc_gateway_wrapper/add_go_package.py
grpc_gateway_wrapper/add_metadata_to_swagger.py
grpc_gateway_wrapper/constants.py
grpc_gateway_wrapper/gen_gateway.py
grpc_gateway_wrapper/gen_gateway_go.py
grpc_gateway_wrapper/gen_openapi_spec.py
grpc_gateway_wrapper/gen_service_spec.py
grpc_gateway_wrapper/log.py
grpc_gateway_wrapper/merge_swagger.py
grpc_gateway_wrapper/parse_proto_files.py
grpc_gateway_wrapper/shell_tools.py
grpc_gateway_wrapper/template_compiler.py
grpc_gateway_wrapper/resources/gateway.go.template
grpc_gateway_wrapper/resources/swagger_serve/favicon-16x16.png
grpc_gateway_wrapper/resources/swagger_serve/favicon-32x32.png
grpc_gateway_wrapper/resources/swagger_serve/index.html
grpc_gateway_wrapper/resources/swagger_serve/swagger-ui-bundle.js
grpc_gateway_wrapper/resources/swagger_serve/swagger-ui-bundle.js.map
grpc_gateway_wrapper/resources/swagger_serve/swagger-ui-standalone-preset.js
grpc_gateway_wrapper/resources/swagger_serve/swagger-ui-standalone-preset.js.map
grpc_gateway_wrapper/resources/swagger_serve/swagger-ui.css
grpc_gateway_wrapper/resources/swagger_serve/swagger-ui.css.map
grpc_gateway_wrapper/resources/swagger_serve/swagger-ui.js
grpc_gateway_wrapper/resources/swagger_serve/swagger-ui.js.map
grpc_gateway_wrapper-0.1.0.dist-info/LICENSE
grpc_gateway_wrapper-0.1.0.dist-info/METADATA
grpc_gateway_wrapper-0.1.0.dist-info/WHEEL
grpc_gateway_wrapper-0.1.0.dist-info/entry_points.txt
grpc_gateway_wrapper-0.1.0.dist-info/top_level.txt
grpc_gateway_wrapper-0.1.0.dist-info/RECORD
