Metadata-Version: 2.1
Name: grpc-gateway-wrapper
Version: 0.1.0
Summary: GRPC Gateway Wrapper
Author: IBM
License: MIT
Requires-Python: ~=3.8
License-File: LICENSE
